[{"year_pub":"1998","atp_code":"2037","asc_code":"2037148000","orgid":"1426","unitid":"189088","sector":"2","org_name":"Bard College","state":"NY","tuition_fees_projected":"N","room_only":null,"room_and_board":null,"tuition_and_fees_in_state":"23095","tuition_and_fees_out_of_state":"23095","tuition_fees_room_and_board_in_state":"23095","tuition_fees_room_and_board_out_of_state":"23095","chrg_tuition_fees_not_avail":null,"hide":"0","pri":"56086"},{"year_pub":"1999","atp_code":"2037","asc_code":"2037148000","orgid":"1426","unitid":"189088","sector":"2","org_name":"Bard College","state":"NY","tuition_fees_projected":"N","room_only":null,"room_and_board":null,"tuition_and_fees_in_state":"24425","tuition_and_fees_out_of_state":"24425","tuition_fees_room_and_board_in_state":"24425","tuition_fees_room_and_board_out_of_state":"24425","chrg_tuition_fees_not_avail":null,"hide":"0","pri":"53055"},{"year_pub":"2000","atp_code":"2037","asc_code":"2037148000","orgid":"1426","unitid":"189088","sector":"2","org_name":"Bard College","state":"NY","tuition_fees_projected":"N","room_only":null,"room_and_board":null,"tuition_and_fees_in_state":"25380","tuition_and_fees_out_of_state":"25380","tuition_fees_room_and_board_in_state":"25380","tuition_fees_room_and_board_out_of_state":"25380","chrg_tuition_fees_not_avail":null,"hide":"0","pri":"50055"},{"year_pub":"2001","atp_code":"2037","asc_code":"2037148000","orgid":"1426","unitid":"189088","sector":"2","org_name":"Bard College","state":"NY","tuition_fees_projected":"N","room_only":null,"room_and_board":null,"tuition_and_fees_in_state":"26400","tuition_and_fees_out_of_state":"26400","tuition_fees_room_and_board_in_state":"26400","tuition_fees_room_and_board_out_of_state":"26400","chrg_tuition_fees_not_avail":null,"hide":"0","pri":"47061"},{"year_pub":"2002","atp_code":"2037","asc_code":"2037148000","orgid":"1426","unitid":"189088","sector":"2","org_name":"Bard College","state":"NY","tuition_fees_projected":"N","room_only":null,"room_and_board":null,"tuition_and_fees_in_state":"27680","tuition_and_fees_out_of_state":"27680","tuition_fees_room_and_board_in_state":"27680","tuition_fees_room_and_board_out_of_state":"27680","chrg_tuition_fees_not_avail":null,"hide":"0","pri":"44224"},{"year_pub":"2003","atp_code":"2037","asc_code":"2037148000","orgid":"1426","unitid":"189088","sector":"2","org_name":"Bard College","state":"NY","tuition_fees_projected":"N","room_only":null,"room_and_board":null,"tuition_and_fees_in_state":"29038","tuition_and_fees_out_of_state":"29038","tuition_fees_room_and_board_in_state":"29038","tuition_fees_room_and_board_out_of_state":"29038","chrg_tuition_fees_not_avail":null,"hide":"0","pri":"41222"},{"year_pub":"2004","atp_code":"2037","asc_code":"2037148000","orgid":"1426","unitid":"189088","sector":"2","org_name":"Bard College","state":"NY","tuition_fees_projected":"N","room_only":null,"room_and_board":null,"tuition_and_fees_in_state":"30650","tuition_and_fees_out_of_state":"30650","tuition_fees_room_and_board_in_state":"30650","tuition_fees_room_and_board_out_of_state":"30650","chrg_tuition_fees_not_avail":null,"hide":"0","pri":"38175"},{"year_pub":"2005","atp_code":"2037","asc_code":"2037148000","orgid":"1426","unitid":"189088","sector":"2","org_name":"Bard College","state":"NY","tuition_fees_projected":"N","room_only":null,"room_and_board":null,"tuition_and_fees_in_state":"32490","tuition_and_fees_out_of_state":"32490","tuition_fees_room_and_board_in_state":"32490","tuition_fees_room_and_board_out_of_state":"32490","chrg_tuition_fees_not_avail":null,"hide":"0","pri":"34968"},{"year_pub":"2006","atp_code":"2037","asc_code":"2037148000","orgid":"1426","unitid":"189088","sector":"2","org_name":"Bard College","state":"NY","tuition_fees_projected":"N","room_only":null,"room_and_board":null,"tuition_and_fees_in_state":"34782","tuition_and_fees_out_of_state":"34782","tuition_fees_room_and_board_in_state":"34782","tuition_fees_room_and_board_out_of_state":"34782","chrg_tuition_fees_not_avail":null,"hide":"0","pri":"31765"},{"year_pub":"2007","atp_code":"2037","asc_code":"2037148000","orgid":"1426","unitid":"189088","sector":"2","org_name":"Bard College","state":"NY","tuition_fees_projected":"N","room_only":null,"room_and_board":null,"tuition_and_fees_in_state":"36534","tuition_and_fees_out_of_state":"36534","tuition_fees_room_and_board_in_state":"36534","tuition_fees_room_and_board_out_of_state":"36534","chrg_tuition_fees_not_avail":null,"hide":"0","pri":"28514"},{"year_pub":"2008","atp_code":"2037","asc_code":"2037148000","orgid":"1426","unitid":"189088","sector":"2","org_name":"Bard College","state":"NY","tuition_fees_projected":"N","room_only":null,"room_and_board":"10866","tuition_and_fees_in_state":"38374","tuition_and_fees_out_of_state":"38374","tuition_fees_room_and_board_in_state":"49240","tuition_fees_room_and_board_out_of_state":"49240","chrg_tuition_fees_not_avail":null,"hide":"0","pri":"25245"},{"year_pub":"2009","atp_code":"2037","asc_code":"2037148000","orgid":"1426","unitid":"189088","sector":"2","org_name":"Bard College","state":"NY","tuition_fees_projected":"N","room_only":null,"room_and_board":"11300","tuition_and_fees_in_state":"39880","tuition_and_fees_out_of_state":"39880","tuition_fees_room_and_board_in_state":"51180","tuition_fees_room_and_board_out_of_state":"51180","chrg_tuition_fees_not_avail":null,"hide":"0","pri":"21978"},{"year_pub":"2010","atp_code":"2037","asc_code":"2037148000","orgid":"1426","unitid":"189088","sector":"2","org_name":"Bard College","state":"NY","tuition_fees_projected":"N","room_only":null,"room_and_board":"11810","tuition_and_fees_in_state":"41670","tuition_and_fees_out_of_state":"41670","tuition_fees_room_and_board_in_state":"53480","tuition_fees_room_and_board_out_of_state":"53480","chrg_tuition_fees_not_avail":null,"hide":"0","pri":"18677"},{"year_pub":"2011","atp_code":"2037","asc_code":"2037148000","orgid":"1426","unitid":"189088","sector":"2","org_name":"Bard College","state":"NY","tuition_fees_projected":"N","room_only":null,"room_and_board":"12286","tuition_and_fees_in_state":"43306","tuition_and_fees_out_of_state":"43306","tuition_fees_room_and_board_in_state":"55592","tuition_fees_room_and_board_out_of_state":"55592","chrg_tuition_fees_not_avail":null,"hide":"0","pri":"15343"},{"year_pub":"2012","atp_code":"2037","asc_code":"2037148000","orgid":"1426","unitid":"189088","sector":"2","org_name":"Bard College","state":"NY","tuition_fees_projected":"N","room_only":null,"room_and_board":"12782","tuition_and_fees_in_state":"44798","tuition_and_fees_out_of_state":"44798","tuition_fees_room_and_board_in_state":"57580","tuition_fees_room_and_board_out_of_state":"57580","chrg_tuition_fees_not_avail":null,"hide":"0","pri":"12068"},{"year_pub":"2013","atp_code":"2037","asc_code":"2037148000","orgid":"1426","unitid":"189088","sector":"2","org_name":"Bard College","state":"NY","tuition_fees_projected":"N","room_only":null,"room_and_board":"13502","tuition_and_fees_in_state":"46370","tuition_and_fees_out_of_state":"46370","tuition_fees_room_and_board_in_state":"59872","tuition_fees_room_and_board_out_of_state":"59872","chrg_tuition_fees_not_avail":null,"hide":"0","pri":"7976"},{"year_pub":"2014","atp_code":"2037","asc_code":"2037148000","orgid":"1426","unitid":"189088","sector":"2","org_name":"Bard College","state":"NY","tuition_fees_projected":"N","room_only":null,"room_and_board":"13772","tuition_and_fees_in_state":"48240","tuition_and_fees_out_of_state":"48240","tuition_fees_room_and_board_in_state":"62012","tuition_fees_room_and_board_out_of_state":"62012","chrg_tuition_fees_not_avail":"N","hide":"0","pri":"5588"},{"year_pub":"2015","atp_code":"2037","asc_code":"2037148000","orgid":"1426","unitid":"189088","sector":"2","org_name":"Bard College","state":"NY","tuition_fees_projected":"N","room_only":null,"room_and_board":"14118","tuition_and_fees_in_state":"49906","tuition_and_fees_out_of_state":"49906","tuition_fees_room_and_board_in_state":"64024","tuition_fees_room_and_board_out_of_state":"64024","chrg_tuition_fees_not_avail":"N","hide":"0","pri":"3088"},{"year_pub":"2016","atp_code":"2037","asc_code":"2037148000","orgid":"1426","unitid":"189088","sector":"2","org_name":"Bard College","state":"NY","tuition_fees_projected":"N","room_only":null,"room_and_board":"14540","tuition_and_fees_in_state":"51614","tuition_and_fees_out_of_state":"51614","tuition_fees_room_and_board_in_state":"66154","tuition_fees_room_and_board_out_of_state":"66154","chrg_tuition_fees_not_avail":"N","hide":"0","pri":"58270"},{"year_pub":"2017","atp_code":"2037","asc_code":"2037148000","orgid":"1426","unitid":"189088","sector":"2","org_name":"Bard College","state":"NY","tuition_fees_projected":"N","room_only":null,"room_and_board":"15066","tuition_and_fees_in_state":"54496","tuition_and_fees_out_of_state":"54496","tuition_fees_room_and_board_in_state":"69562","tuition_fees_room_and_board_out_of_state":"69562","chrg_tuition_fees_not_avail":"N","hide":"0","pri":"62984"},{"year_pub":"2018","atp_code":"2037","asc_code":"2037148000","orgid":"1426","unitid":"189088","sector":"2","org_name":"Bard College","state":"NY","tuition_fees_projected":"N","room_only":null,"room_and_board":"15488","tuition_and_fees_in_state":"54680","tuition_and_fees_out_of_state":"54680","tuition_fees_room_and_board_in_state":"70168","tuition_fees_room_and_board_out_of_state":"70168","chrg_tuition_fees_not_avail":"N","hide":"0","pri":"68471"}]