[{"year_pub":"1998","atp_code":"2299","asc_code":"2299023500","orgid":"1160","unitid":"191676","sector":"2","org_name":"Houghton College","state":"NY","tuition_fees_projected":"N","room_only":null,"room_and_board":null,"tuition_and_fees_in_state":"12790","tuition_and_fees_out_of_state":"12790","tuition_fees_room_and_board_in_state":"12790","tuition_fees_room_and_board_out_of_state":"12790","chrg_tuition_fees_not_avail":null,"hide":"0","pri":"56136"},{"year_pub":"1999","atp_code":"2299","asc_code":"2299023500","orgid":"1160","unitid":"191676","sector":"2","org_name":"Houghton College","state":"NY","tuition_fees_projected":"N","room_only":null,"room_and_board":null,"tuition_and_fees_in_state":"14590","tuition_and_fees_out_of_state":"14590","tuition_fees_room_and_board_in_state":"14590","tuition_fees_room_and_board_out_of_state":"14590","chrg_tuition_fees_not_avail":null,"hide":"0","pri":"53105"},{"year_pub":"2000","atp_code":"2299","asc_code":"2299023500","orgid":"1160","unitid":"191676","sector":"2","org_name":"Houghton College","state":"NY","tuition_fees_projected":"N","room_only":null,"room_and_board":null,"tuition_and_fees_in_state":"15180","tuition_and_fees_out_of_state":"15180","tuition_fees_room_and_board_in_state":"15180","tuition_fees_room_and_board_out_of_state":"15180","chrg_tuition_fees_not_avail":null,"hide":"0","pri":"50107"},{"year_pub":"2001","atp_code":"2299","asc_code":"2299023500","orgid":"1160","unitid":"191676","sector":"2","org_name":"Houghton College","state":"NY","tuition_fees_projected":"N","room_only":null,"room_and_board":null,"tuition_and_fees_in_state":"16290","tuition_and_fees_out_of_state":"16290","tuition_fees_room_and_board_in_state":"16290","tuition_fees_room_and_board_out_of_state":"16290","chrg_tuition_fees_not_avail":null,"hide":"0","pri":"47109"},{"year_pub":"2002","atp_code":"2299","asc_code":"2299023500","orgid":"1160","unitid":"191676","sector":"2","org_name":"Houghton College","state":"NY","tuition_fees_projected":"N","room_only":null,"room_and_board":null,"tuition_and_fees_in_state":"17160","tuition_and_fees_out_of_state":"17160","tuition_fees_room_and_board_in_state":"17160","tuition_fees_room_and_board_out_of_state":"17160","chrg_tuition_fees_not_avail":null,"hide":"0","pri":"44269"},{"year_pub":"2003","atp_code":"2299","asc_code":"2299023500","orgid":"1160","unitid":"191676","sector":"2","org_name":"Houghton College","state":"NY","tuition_fees_projected":"N","room_only":null,"room_and_board":null,"tuition_and_fees_in_state":"17984","tuition_and_fees_out_of_state":"17984","tuition_fees_room_and_board_in_state":"17984","tuition_fees_room_and_board_out_of_state":"17984","chrg_tuition_fees_not_avail":null,"hide":"0","pri":"41271"},{"year_pub":"2004","atp_code":"2299","asc_code":"2299023500","orgid":"1160","unitid":"191676","sector":"2","org_name":"Houghton College","state":"NY","tuition_fees_projected":"N","room_only":null,"room_and_board":null,"tuition_and_fees_in_state":"18660","tuition_and_fees_out_of_state":"18660","tuition_fees_room_and_board_in_state":"18660","tuition_fees_room_and_board_out_of_state":"18660","chrg_tuition_fees_not_avail":null,"hide":"0","pri":"38229"},{"year_pub":"2005","atp_code":"2299","asc_code":"2299023500","orgid":"1160","unitid":"191676","sector":"2","org_name":"Houghton College","state":"NY","tuition_fees_projected":"N","room_only":null,"room_and_board":null,"tuition_and_fees_in_state":"19420","tuition_and_fees_out_of_state":"19420","tuition_fees_room_and_board_in_state":"19420","tuition_fees_room_and_board_out_of_state":"19420","chrg_tuition_fees_not_avail":null,"hide":"0","pri":"35022"},{"year_pub":"2006","atp_code":"2299","asc_code":"2299023500","orgid":"1160","unitid":"191676","sector":"2","org_name":"Houghton College","state":"NY","tuition_fees_projected":"N","room_only":null,"room_and_board":null,"tuition_and_fees_in_state":"20400","tuition_and_fees_out_of_state":"20400","tuition_fees_room_and_board_in_state":"20400","tuition_fees_room_and_board_out_of_state":"20400","chrg_tuition_fees_not_avail":null,"hide":"0","pri":"31822"},{"year_pub":"2007","atp_code":"2299","asc_code":"2299023500","orgid":"1160","unitid":"191676","sector":"2","org_name":"Houghton College","state":"NY","tuition_fees_projected":"N","room_only":null,"room_and_board":null,"tuition_and_fees_in_state":"21624","tuition_and_fees_out_of_state":"21624","tuition_fees_room_and_board_in_state":"21624","tuition_fees_room_and_board_out_of_state":"21624","chrg_tuition_fees_not_avail":null,"hide":"0","pri":"28568"},{"year_pub":"2008","atp_code":"2299","asc_code":"2299023500","orgid":"1160","unitid":"191676","sector":"2","org_name":"Houghton College","state":"NY","tuition_fees_projected":"N","room_only":null,"room_and_board":"6930","tuition_and_fees_in_state":"22990","tuition_and_fees_out_of_state":"22990","tuition_fees_room_and_board_in_state":"29920","tuition_fees_room_and_board_out_of_state":"29920","chrg_tuition_fees_not_avail":null,"hide":"0","pri":"25302"},{"year_pub":"2009","atp_code":"2299","asc_code":"2299023500","orgid":"1160","unitid":"191676","sector":"2","org_name":"Houghton College","state":"NY","tuition_fees_projected":"N","room_only":null,"room_and_board":"7000","tuition_and_fees_in_state":"24440","tuition_and_fees_out_of_state":"24440","tuition_fees_room_and_board_in_state":"31440","tuition_fees_room_and_board_out_of_state":"31440","chrg_tuition_fees_not_avail":null,"hide":"0","pri":"22037"},{"year_pub":"2010","atp_code":"2299","asc_code":"2299023500","orgid":"1160","unitid":"191676","sector":"2","org_name":"Houghton College","state":"NY","tuition_fees_projected":"N","room_only":null,"room_and_board":"7330","tuition_and_fees_in_state":"25360","tuition_and_fees_out_of_state":"25360","tuition_fees_room_and_board_in_state":"32690","tuition_fees_room_and_board_out_of_state":"32690","chrg_tuition_fees_not_avail":null,"hide":"0","pri":"18742"},{"year_pub":"2011","atp_code":"2299","asc_code":"2299023500","orgid":"1160","unitid":"191676","sector":"2","org_name":"Houghton College","state":"NY","tuition_fees_projected":"N","room_only":null,"room_and_board":"7550","tuition_and_fees_in_state":"26094","tuition_and_fees_out_of_state":"26094","tuition_fees_room_and_board_in_state":"33644","tuition_fees_room_and_board_out_of_state":"33644","chrg_tuition_fees_not_avail":null,"hide":"0","pri":"15412"},{"year_pub":"2012","atp_code":"2299","asc_code":"2299023500","orgid":"1160","unitid":"191676","sector":"2","org_name":"Houghton College","state":"NY","tuition_fees_projected":"N","room_only":null,"room_and_board":"7778","tuition_and_fees_in_state":"26924","tuition_and_fees_out_of_state":"26924","tuition_fees_room_and_board_in_state":"34702","tuition_fees_room_and_board_out_of_state":"34702","chrg_tuition_fees_not_avail":null,"hide":"0","pri":"12134"},{"year_pub":"2013","atp_code":"2299","asc_code":"2299023500","orgid":"1160","unitid":"191676","sector":"2","org_name":"Houghton College","state":"NY","tuition_fees_projected":"N","room_only":null,"room_and_board":"8012","tuition_and_fees_in_state":"27728","tuition_and_fees_out_of_state":"27728","tuition_fees_room_and_board_in_state":"35740","tuition_fees_room_and_board_out_of_state":"35740","chrg_tuition_fees_not_avail":null,"hide":"0","pri":"8963"},{"year_pub":"2014","atp_code":"2299","asc_code":"2299023500","orgid":"1160","unitid":"191676","sector":"2","org_name":"Houghton College","state":"NY","tuition_fees_projected":"N","room_only":null,"room_and_board":"8252","tuition_and_fees_in_state":"28556","tuition_and_fees_out_of_state":"28556","tuition_fees_room_and_board_in_state":"36808","tuition_fees_room_and_board_out_of_state":"36808","chrg_tuition_fees_not_avail":"N","hide":"0","pri":"4568"},{"year_pub":"2015","atp_code":"2299","asc_code":"2299023500","orgid":"1160","unitid":"191676","sector":"2","org_name":"Houghton College","state":"NY","tuition_fees_projected":"N","room_only":null,"room_and_board":"8498","tuition_and_fees_in_state":"29458","tuition_and_fees_out_of_state":"29458","tuition_fees_room_and_board_in_state":"37956","tuition_fees_room_and_board_out_of_state":"37956","chrg_tuition_fees_not_avail":"N","hide":"0","pri":"1969"},{"year_pub":"2016","atp_code":"2299","asc_code":"2299023500","orgid":"1160","unitid":"191676","sector":"2","org_name":"Houghton College","state":"NY","tuition_fees_projected":"N","room_only":null,"room_and_board":"8754","tuition_and_fees_in_state":"30336","tuition_and_fees_out_of_state":"30336","tuition_fees_room_and_board_in_state":"39090","tuition_fees_room_and_board_out_of_state":"39090","chrg_tuition_fees_not_avail":"N","hide":"0","pri":"59431"},{"year_pub":"2017","atp_code":"2299","asc_code":"2299023500","orgid":"1160","unitid":"191676","sector":"2","org_name":"Houghton College","state":"NY","tuition_fees_projected":"N","room_only":null,"room_and_board":"9018","tuition_and_fees_in_state":"31540","tuition_and_fees_out_of_state":"31540","tuition_fees_room_and_board_in_state":"40558","tuition_fees_room_and_board_out_of_state":"40558","chrg_tuition_fees_not_avail":"N","hide":"0","pri":"62752"},{"year_pub":"2018","atp_code":"2299","asc_code":"2299023500","orgid":"1160","unitid":"191676","sector":"2","org_name":"Houghton College","state":"NY","tuition_fees_projected":"N","room_only":null,"room_and_board":"9288","tuition_and_fees_in_state":"32488","tuition_and_fees_out_of_state":"32488","tuition_fees_room_and_board_in_state":"41776","tuition_fees_room_and_board_out_of_state":"41776","chrg_tuition_fees_not_avail":"N","hide":"0","pri":"67988"}]