[{"year_pub":"2005","atp_code":"4127","asc_code":"5906464600","orgid":"1081","unitid":"428392","sector":"4","org_name":"Klamath Community College","state":"OR","tuition_fees_projected":"N","room_only":null,"room_and_board":null,"tuition_and_fees_in_state":"2805","tuition_and_fees_out_of_state":"6315","tuition_fees_room_and_board_in_state":"2805","tuition_fees_room_and_board_out_of_state":"6315","chrg_tuition_fees_not_avail":null,"hide":"0","pri":"34758"},{"year_pub":"2006","atp_code":"4127","asc_code":"5906464600","orgid":"1081","unitid":"428392","sector":"4","org_name":"Klamath Community College","state":"OR","tuition_fees_projected":"N","room_only":null,"room_and_board":null,"tuition_and_fees_in_state":"2940","tuition_and_fees_out_of_state":"6450","tuition_fees_room_and_board_in_state":"2940","tuition_fees_room_and_board_out_of_state":"6450","chrg_tuition_fees_not_avail":null,"hide":"0","pri":"31546"},{"year_pub":"2007","atp_code":"4127","asc_code":"5906464600","orgid":"1081","unitid":"428392","sector":"4","org_name":"Klamath Community College","state":"OR","tuition_fees_projected":"N","room_only":null,"room_and_board":null,"tuition_and_fees_in_state":"2940","tuition_and_fees_out_of_state":"6450","tuition_fees_room_and_board_in_state":"2940","tuition_fees_room_and_board_out_of_state":"6450","chrg_tuition_fees_not_avail":null,"hide":"0","pri":"28304"},{"year_pub":"2008","atp_code":"4127","asc_code":"5906464600","orgid":"1081","unitid":"428392","sector":"4","org_name":"Klamath Community College","state":"OR","tuition_fees_projected":"N","room_only":null,"room_and_board":null,"tuition_and_fees_in_state":"3020","tuition_and_fees_out_of_state":"6470","tuition_fees_room_and_board_in_state":"3020","tuition_fees_room_and_board_out_of_state":"6470","chrg_tuition_fees_not_avail":null,"hide":"0","pri":"25029"},{"year_pub":"2009","atp_code":"4127","asc_code":"5906464600","orgid":"1081","unitid":"428392","sector":"4","org_name":"Klamath Community College","state":"OR","tuition_fees_projected":"N","room_only":null,"room_and_board":null,"tuition_and_fees_in_state":"3435","tuition_and_fees_out_of_state":"6945","tuition_fees_room_and_board_in_state":"3435","tuition_fees_room_and_board_out_of_state":"6945","chrg_tuition_fees_not_avail":null,"hide":"0","pri":"21783"},{"year_pub":"2010","atp_code":"4127","asc_code":"5906464600","orgid":"1081","unitid":"428392","sector":"4","org_name":"Klamath Community College","state":"OR","tuition_fees_projected":"N","room_only":null,"room_and_board":null,"tuition_and_fees_in_state":"3605","tuition_and_fees_out_of_state":"7115","tuition_fees_room_and_board_in_state":"3605","tuition_fees_room_and_board_out_of_state":"7115","chrg_tuition_fees_not_avail":null,"hide":"0","pri":"18482"},{"year_pub":"2011","atp_code":"4127","asc_code":"5906464600","orgid":"1081","unitid":"428392","sector":"4","org_name":"Klamath Community College","state":"OR","tuition_fees_projected":"N","room_only":null,"room_and_board":null,"tuition_and_fees_in_state":"3840","tuition_and_fees_out_of_state":"7350","tuition_fees_room_and_board_in_state":"3840","tuition_fees_room_and_board_out_of_state":"7350","chrg_tuition_fees_not_avail":null,"hide":"0","pri":"15148"},{"year_pub":"2012","atp_code":"4127","asc_code":"5906464600","orgid":"1081","unitid":"428392","sector":"4","org_name":"Klamath Community College","state":"OR","tuition_fees_projected":"N","room_only":null,"room_and_board":null,"tuition_and_fees_in_state":"4290","tuition_and_fees_out_of_state":"7800","tuition_fees_room_and_board_in_state":"4290","tuition_fees_room_and_board_out_of_state":"7800","chrg_tuition_fees_not_avail":null,"hide":"0","pri":"11875"},{"year_pub":"2013","atp_code":"4127","asc_code":"5906464600","orgid":"1081","unitid":"428392","sector":"4","org_name":"Klamath Community College","state":"OR","tuition_fees_projected":"N","room_only":null,"room_and_board":null,"tuition_and_fees_in_state":"4290","tuition_and_fees_out_of_state":"7800","tuition_fees_room_and_board_in_state":"4290","tuition_fees_room_and_board_out_of_state":"7800","chrg_tuition_fees_not_avail":null,"hide":"0","pri":"9154"},{"year_pub":"2014","atp_code":"4127","asc_code":"5906464600","orgid":"1081","unitid":"428392","sector":"4","org_name":"Klamath Community College","state":"OR","tuition_fees_projected":"N","room_only":null,"room_and_board":null,"tuition_and_fees_in_state":"4606","tuition_and_fees_out_of_state":"7823","tuition_fees_room_and_board_in_state":"4606","tuition_fees_room_and_board_out_of_state":"7823","chrg_tuition_fees_not_avail":"N","hide":"0","pri":"6678"},{"year_pub":"2015","atp_code":"4127","asc_code":"5906464600","orgid":"1081","unitid":"428392","sector":"4","org_name":"Klamath Community College","state":"OR","tuition_fees_projected":"N","room_only":null,"room_and_board":null,"tuition_and_fees_in_state":"4606","tuition_and_fees_out_of_state":"7823","tuition_fees_room_and_board_in_state":"4606","tuition_fees_room_and_board_out_of_state":"7823","chrg_tuition_fees_not_avail":"N","hide":"0","pri":"1724"},{"year_pub":"2016","atp_code":"4127","asc_code":"5906464600","orgid":"1081","unitid":"428392","sector":"4","org_name":"Klamath Community College","state":"OR","tuition_fees_projected":"N","room_only":null,"room_and_board":null,"tuition_and_fees_in_state":"4606","tuition_and_fees_out_of_state":"7823","tuition_fees_room_and_board_in_state":"4606","tuition_fees_room_and_board_out_of_state":"7823","chrg_tuition_fees_not_avail":"N","hide":"0","pri":"59662"},{"year_pub":"2017","atp_code":"4127","asc_code":"5906464600","orgid":"1081","unitid":"428392","sector":"4","org_name":"Klamath Community College","state":"OR","tuition_fees_projected":"N","room_only":null,"room_and_board":null,"tuition_and_fees_in_state":"5197","tuition_and_fees_out_of_state":"8100","tuition_fees_room_and_board_in_state":"5197","tuition_fees_room_and_board_out_of_state":"8100","chrg_tuition_fees_not_avail":"N","hide":"0","pri":"62695"},{"year_pub":"2018","atp_code":"4127","asc_code":"5906464600","orgid":"1081","unitid":"428392","sector":"4","org_name":"Klamath Community College","state":"OR","tuition_fees_projected":"N","room_only":null,"room_and_board":null,"tuition_and_fees_in_state":"5496","tuition_and_fees_out_of_state":"8714","tuition_fees_room_and_board_in_state":"5496","tuition_fees_room_and_board_out_of_state":"8714","chrg_tuition_fees_not_avail":"N","hide":"0","pri":"66428"}]