[{"year_pub":"1998","atp_code":"6390","asc_code":"6390053100","orgid":"480","unitid":"173902","sector":"2","org_name":"Macalester College","state":"MN","tuition_fees_projected":"N","room_only":null,"room_and_board":null,"tuition_and_fees_in_state":"19801","tuition_and_fees_out_of_state":"19801","tuition_fees_room_and_board_in_state":"19801","tuition_fees_room_and_board_out_of_state":"19801","chrg_tuition_fees_not_avail":null,"hide":"0","pri":"56697"},{"year_pub":"1999","atp_code":"6390","asc_code":"6390053100","orgid":"480","unitid":"173902","sector":"2","org_name":"Macalester College","state":"MN","tuition_fees_projected":"N","room_only":null,"room_and_board":null,"tuition_and_fees_in_state":"20688","tuition_and_fees_out_of_state":"20688","tuition_fees_room_and_board_in_state":"20688","tuition_fees_room_and_board_out_of_state":"20688","chrg_tuition_fees_not_avail":null,"hide":"0","pri":"53666"},{"year_pub":"2000","atp_code":"6390","asc_code":"6390053100","orgid":"480","unitid":"173902","sector":"2","org_name":"Macalester College","state":"MN","tuition_fees_projected":"N","room_only":null,"room_and_board":null,"tuition_and_fees_in_state":"21614","tuition_and_fees_out_of_state":"21614","tuition_fees_room_and_board_in_state":"21614","tuition_fees_room_and_board_out_of_state":"21614","chrg_tuition_fees_not_avail":null,"hide":"0","pri":"50659"},{"year_pub":"2001","atp_code":"6390","asc_code":"6390053100","orgid":"480","unitid":"173902","sector":"2","org_name":"Macalester College","state":"MN","tuition_fees_projected":"N","room_only":null,"room_and_board":null,"tuition_and_fees_in_state":"22608","tuition_and_fees_out_of_state":"22608","tuition_fees_room_and_board_in_state":"22608","tuition_fees_room_and_board_out_of_state":"22608","chrg_tuition_fees_not_avail":null,"hide":"0","pri":"47580"},{"year_pub":"2002","atp_code":"6390","asc_code":"6390053100","orgid":"480","unitid":"173902","sector":"2","org_name":"Macalester College","state":"MN","tuition_fees_projected":"N","room_only":null,"room_and_board":null,"tuition_and_fees_in_state":"23772","tuition_and_fees_out_of_state":"23772","tuition_fees_room_and_board_in_state":"23772","tuition_fees_room_and_board_out_of_state":"23772","chrg_tuition_fees_not_avail":null,"hide":"0","pri":"44716"},{"year_pub":"2003","atp_code":"6390","asc_code":"6390053100","orgid":"480","unitid":"173902","sector":"2","org_name":"Macalester College","state":"MN","tuition_fees_projected":"N","room_only":null,"room_and_board":null,"tuition_and_fees_in_state":"25070","tuition_and_fees_out_of_state":"25070","tuition_fees_room_and_board_in_state":"25070","tuition_fees_room_and_board_out_of_state":"25070","chrg_tuition_fees_not_avail":null,"hide":"0","pri":"41791"},{"year_pub":"2004","atp_code":"6390","asc_code":"6390053100","orgid":"480","unitid":"173902","sector":"2","org_name":"Macalester College","state":"MN","tuition_fees_projected":"N","room_only":null,"room_and_board":null,"tuition_and_fees_in_state":"26806","tuition_and_fees_out_of_state":"26806","tuition_fees_room_and_board_in_state":"26806","tuition_fees_room_and_board_out_of_state":"26806","chrg_tuition_fees_not_avail":null,"hide":"0","pri":"38761"},{"year_pub":"2005","atp_code":"6390","asc_code":"6390053100","orgid":"480","unitid":"173902","sector":"2","org_name":"Macalester College","state":"MN","tuition_fees_projected":"N","room_only":null,"room_and_board":null,"tuition_and_fees_in_state":"28642","tuition_and_fees_out_of_state":"28642","tuition_fees_room_and_board_in_state":"28642","tuition_fees_room_and_board_out_of_state":"28642","chrg_tuition_fees_not_avail":null,"hide":"0","pri":"35619"},{"year_pub":"2006","atp_code":"6390","asc_code":"6390053100","orgid":"480","unitid":"173902","sector":"2","org_name":"Macalester College","state":"MN","tuition_fees_projected":"N","room_only":null,"room_and_board":null,"tuition_and_fees_in_state":"31038","tuition_and_fees_out_of_state":"31038","tuition_fees_room_and_board_in_state":"31038","tuition_fees_room_and_board_out_of_state":"31038","chrg_tuition_fees_not_avail":null,"hide":"0","pri":"32436"},{"year_pub":"2007","atp_code":"6390","asc_code":"6390053100","orgid":"480","unitid":"173902","sector":"2","org_name":"Macalester College","state":"MN","tuition_fees_projected":"N","room_only":null,"room_and_board":null,"tuition_and_fees_in_state":"33694","tuition_and_fees_out_of_state":"33694","tuition_fees_room_and_board_in_state":"33694","tuition_fees_room_and_board_out_of_state":"33694","chrg_tuition_fees_not_avail":null,"hide":"0","pri":"29176"},{"year_pub":"2008","atp_code":"6390","asc_code":"6390053100","orgid":"480","unitid":"173902","sector":"2","org_name":"Macalester College","state":"MN","tuition_fees_projected":"N","room_only":null,"room_and_board":"8472","tuition_and_fees_in_state":"36504","tuition_and_fees_out_of_state":"36504","tuition_fees_room_and_board_in_state":"44976","tuition_fees_room_and_board_out_of_state":"44976","chrg_tuition_fees_not_avail":null,"hide":"0","pri":"25916"},{"year_pub":"2009","atp_code":"6390","asc_code":"6390053100","orgid":"480","unitid":"173902","sector":"2","org_name":"Macalester College","state":"MN","tuition_fees_projected":"N","room_only":null,"room_and_board":"8768","tuition_and_fees_in_state":"38174","tuition_and_fees_out_of_state":"38174","tuition_fees_room_and_board_in_state":"46942","tuition_fees_room_and_board_out_of_state":"46942","chrg_tuition_fees_not_avail":null,"hide":"0","pri":"22631"},{"year_pub":"2010","atp_code":"6390","asc_code":"6390053100","orgid":"480","unitid":"173902","sector":"2","org_name":"Macalester College","state":"MN","tuition_fees_projected":"N","room_only":null,"room_and_board":"9078","tuition_and_fees_in_state":"40046","tuition_and_fees_out_of_state":"40046","tuition_fees_room_and_board_in_state":"49124","tuition_fees_room_and_board_out_of_state":"49124","chrg_tuition_fees_not_avail":null,"hide":"0","pri":"19364"},{"year_pub":"2011","atp_code":"6390","asc_code":"6390053100","orgid":"480","unitid":"173902","sector":"2","org_name":"Macalester College","state":"MN","tuition_fees_projected":"N","room_only":null,"room_and_board":"9396","tuition_and_fees_in_state":"42021","tuition_and_fees_out_of_state":"42021","tuition_fees_room_and_board_in_state":"51417","tuition_fees_room_and_board_out_of_state":"51417","chrg_tuition_fees_not_avail":null,"hide":"0","pri":"16031"},{"year_pub":"2012","atp_code":"6390","asc_code":"6390053100","orgid":"480","unitid":"173902","sector":"2","org_name":"Macalester College","state":"MN","tuition_fees_projected":"N","room_only":null,"room_and_board":"9726","tuition_and_fees_in_state":"43693","tuition_and_fees_out_of_state":"43693","tuition_fees_room_and_board_in_state":"53419","tuition_fees_room_and_board_out_of_state":"53419","chrg_tuition_fees_not_avail":null,"hide":"0","pri":"12726"},{"year_pub":"2013","atp_code":"6390","asc_code":"6390053100","orgid":"480","unitid":"173902","sector":"2","org_name":"Macalester College","state":"MN","tuition_fees_projected":"N","room_only":null,"room_and_board":"10068","tuition_and_fees_in_state":"45388","tuition_and_fees_out_of_state":"45388","tuition_fees_room_and_board_in_state":"55456","tuition_fees_room_and_board_out_of_state":"55456","chrg_tuition_fees_not_avail":null,"hide":"0","pri":"9293"},{"year_pub":"2014","atp_code":"6390","asc_code":"6390053100","orgid":"480","unitid":"173902","sector":"2","org_name":"Macalester College","state":"MN","tuition_fees_projected":"N","room_only":null,"room_and_board":"10496","tuition_and_fees_in_state":"47195","tuition_and_fees_out_of_state":"47195","tuition_fees_room_and_board_in_state":"57691","tuition_fees_room_and_board_out_of_state":"57691","chrg_tuition_fees_not_avail":"N","hide":"0","pri":"5115"},{"year_pub":"2015","atp_code":"6390","asc_code":"6390053100","orgid":"480","unitid":"173902","sector":"2","org_name":"Macalester College","state":"MN","tuition_fees_projected":"N","room_only":null,"room_and_board":"10874","tuition_and_fees_in_state":"48887","tuition_and_fees_out_of_state":"48887","tuition_fees_room_and_board_in_state":"59761","tuition_fees_room_and_board_out_of_state":"59761","chrg_tuition_fees_not_avail":"N","hide":"0","pri":"2563"},{"year_pub":"2016","atp_code":"6390","asc_code":"6390053100","orgid":"480","unitid":"173902","sector":"2","org_name":"Macalester College","state":"MN","tuition_fees_projected":"N","room_only":null,"room_and_board":"11266","tuition_and_fees_in_state":"50639","tuition_and_fees_out_of_state":"50639","tuition_fees_room_and_board_in_state":"61905","tuition_fees_room_and_board_out_of_state":"61905","chrg_tuition_fees_not_avail":"N","hide":"0","pri":"59827"},{"year_pub":"2017","atp_code":"6390","asc_code":"6390053100","orgid":"480","unitid":"173902","sector":"2","org_name":"Macalester College","state":"MN","tuition_fees_projected":"N","room_only":null,"room_and_board":"11672","tuition_and_fees_in_state":"52464","tuition_and_fees_out_of_state":"52464","tuition_fees_room_and_board_in_state":"64136","tuition_fees_room_and_board_out_of_state":"64136","chrg_tuition_fees_not_avail":"N","hide":"0","pri":"62177"},{"year_pub":"2018","atp_code":"6390","asc_code":"6390053100","orgid":"480","unitid":"173902","sector":"2","org_name":"Macalester College","state":"MN","tuition_fees_projected":"N","room_only":null,"room_and_board":"12156","tuition_and_fees_in_state":"54344","tuition_and_fees_out_of_state":"54344","tuition_fees_room_and_board_in_state":"66500","tuition_fees_room_and_board_out_of_state":"66500","chrg_tuition_fees_not_avail":"N","hide":"0","pri":"68459"}]