[{"year_pub":"1998","atp_code":"1893","asc_code":"1893281900","orgid":"1214","unitid":"222062","sector":"4","org_name":"Walters State Community College","state":"TN","tuition_fees_projected":"N","room_only":null,"room_and_board":null,"tuition_and_fees_in_state":"1244","tuition_and_fees_out_of_state":"1244","tuition_fees_room_and_board_in_state":"1244","tuition_fees_room_and_board_out_of_state":"1244","chrg_tuition_fees_not_avail":null,"hide":"0","pri":"55448"},{"year_pub":"1999","atp_code":"1893","asc_code":"1893281900","orgid":"1214","unitid":"222062","sector":"4","org_name":"Walters State Community College","state":"TN","tuition_fees_projected":"N","room_only":null,"room_and_board":null,"tuition_and_fees_in_state":"1308","tuition_and_fees_out_of_state":"4896","tuition_fees_room_and_board_in_state":"1308","tuition_fees_room_and_board_out_of_state":"4896","chrg_tuition_fees_not_avail":null,"hide":"0","pri":"52417"},{"year_pub":"2000","atp_code":"1893","asc_code":"1893281900","orgid":"1214","unitid":"222062","sector":"4","org_name":"Walters State Community College","state":"TN","tuition_fees_projected":"N","room_only":null,"room_and_board":null,"tuition_and_fees_in_state":"1433","tuition_and_fees_out_of_state":"5309","tuition_fees_room_and_board_in_state":"1433","tuition_fees_room_and_board_out_of_state":"5309","chrg_tuition_fees_not_avail":null,"hide":"0","pri":"49417"},{"year_pub":"2001","atp_code":"1893","asc_code":"1893281900","orgid":"1214","unitid":"222062","sector":"4","org_name":"Walters State Community College","state":"TN","tuition_fees_projected":"N","room_only":null,"room_and_board":null,"tuition_and_fees_in_state":"1627","tuition_and_fees_out_of_state":"6085","tuition_fees_room_and_board_in_state":"1627","tuition_fees_room_and_board_out_of_state":"6085","chrg_tuition_fees_not_avail":null,"hide":"0","pri":"46421"},{"year_pub":"2002","atp_code":"1893","asc_code":"1893281900","orgid":"1214","unitid":"222062","sector":"4","org_name":"Walters State Community College","state":"TN","tuition_fees_projected":"N","room_only":null,"room_and_board":null,"tuition_and_fees_in_state":"1771","tuition_and_fees_out_of_state":"6563","tuition_fees_room_and_board_in_state":"1771","tuition_fees_room_and_board_out_of_state":"6563","chrg_tuition_fees_not_avail":null,"hide":"0","pri":"43580"},{"year_pub":"2003","atp_code":"1893","asc_code":"1893281900","orgid":"1214","unitid":"222062","sector":"4","org_name":"Walters State Community College","state":"TN","tuition_fees_projected":"N","room_only":null,"room_and_board":null,"tuition_and_fees_in_state":"2062","tuition_and_fees_out_of_state":"7526","tuition_fees_room_and_board_in_state":"2062","tuition_fees_room_and_board_out_of_state":"7526","chrg_tuition_fees_not_avail":null,"hide":"0","pri":"40606"},{"year_pub":"2004","atp_code":"1893","asc_code":"1893281900","orgid":"1214","unitid":"222062","sector":"4","org_name":"Walters State Community College","state":"TN","tuition_fees_projected":"N","room_only":null,"room_and_board":null,"tuition_and_fees_in_state":"2187","tuition_and_fees_out_of_state":"8033","tuition_fees_room_and_board_in_state":"2187","tuition_fees_room_and_board_out_of_state":"8033","chrg_tuition_fees_not_avail":null,"hide":"0","pri":"37519"},{"year_pub":"2005","atp_code":"1893","asc_code":"1893281900","orgid":"1214","unitid":"222062","sector":"4","org_name":"Walters State Community College","state":"TN","tuition_fees_projected":"N","room_only":null,"room_and_board":null,"tuition_and_fees_in_state":"2381","tuition_and_fees_out_of_state":"8795","tuition_fees_room_and_board_in_state":"2381","tuition_fees_room_and_board_out_of_state":"8795","chrg_tuition_fees_not_avail":null,"hide":"0","pri":"34424"},{"year_pub":"2006","atp_code":"1893","asc_code":"1893281900","orgid":"1214","unitid":"222062","sector":"4","org_name":"Walters State Community College","state":"TN","tuition_fees_projected":"N","room_only":null,"room_and_board":null,"tuition_and_fees_in_state":"2469","tuition_and_fees_out_of_state":"9146","tuition_fees_room_and_board_in_state":"2469","tuition_fees_room_and_board_out_of_state":"9146","chrg_tuition_fees_not_avail":null,"hide":"0","pri":"31187"},{"year_pub":"2007","atp_code":"1893","asc_code":"1893281900","orgid":"1214","unitid":"222062","sector":"4","org_name":"Walters State Community College","state":"TN","tuition_fees_projected":"N","room_only":null,"room_and_board":null,"tuition_and_fees_in_state":"2637","tuition_and_fees_out_of_state":"10043","tuition_fees_room_and_board_in_state":"2637","tuition_fees_room_and_board_out_of_state":"10043","chrg_tuition_fees_not_avail":null,"hide":"0","pri":"27934"},{"year_pub":"2008","atp_code":"1893","asc_code":"1893281900","orgid":"1214","unitid":"222062","sector":"4","org_name":"Walters State Community College","state":"TN","tuition_fees_projected":"N","room_only":null,"room_and_board":null,"tuition_and_fees_in_state":"2775","tuition_and_fees_out_of_state":"10275","tuition_fees_room_and_board_in_state":"2775","tuition_fees_room_and_board_out_of_state":"10275","chrg_tuition_fees_not_avail":null,"hide":"0","pri":"24675"},{"year_pub":"2009","atp_code":"1893","asc_code":"1893281900","orgid":"1214","unitid":"222062","sector":"4","org_name":"Walters State Community College","state":"TN","tuition_fees_projected":"N","room_only":null,"room_and_board":null,"tuition_and_fees_in_state":"2969","tuition_and_fees_out_of_state":"11453","tuition_fees_room_and_board_in_state":"2969","tuition_fees_room_and_board_out_of_state":"11453","chrg_tuition_fees_not_avail":null,"hide":"0","pri":"21429"},{"year_pub":"2010","atp_code":"1893","asc_code":"1893281900","orgid":"1214","unitid":"222062","sector":"4","org_name":"Walters State Community College","state":"TN","tuition_fees_projected":"N","room_only":null,"room_and_board":null,"tuition_and_fees_in_state":"3209","tuition_and_fees_out_of_state":"12395","tuition_fees_room_and_board_in_state":"3209","tuition_fees_room_and_board_out_of_state":"12395","chrg_tuition_fees_not_avail":null,"hide":"0","pri":"18120"},{"year_pub":"2011","atp_code":"1893","asc_code":"1893281900","orgid":"1214","unitid":"222062","sector":"4","org_name":"Walters State Community College","state":"TN","tuition_fees_projected":"N","room_only":null,"room_and_board":null,"tuition_and_fees_in_state":"3531","tuition_and_fees_out_of_state":"13635","tuition_fees_room_and_board_in_state":"3531","tuition_fees_room_and_board_out_of_state":"13635","chrg_tuition_fees_not_avail":null,"hide":"0","pri":"14812"},{"year_pub":"2012","atp_code":"1893","asc_code":"1893281900","orgid":"1214","unitid":"222062","sector":"4","org_name":"Walters State Community College","state":"TN","tuition_fees_projected":"N","room_only":null,"room_and_board":null,"tuition_and_fees_in_state":"3681","tuition_and_fees_out_of_state":"14313","tuition_fees_room_and_board_in_state":"3681","tuition_fees_room_and_board_out_of_state":"14313","chrg_tuition_fees_not_avail":null,"hide":"0","pri":"11531"},{"year_pub":"2013","atp_code":"1893","asc_code":"1893281900","orgid":"1214","unitid":"222062","sector":"4","org_name":"Walters State Community College","state":"TN","tuition_fees_projected":"N","room_only":null,"room_and_board":null,"tuition_and_fees_in_state":"3783","tuition_and_fees_out_of_state":"14745","tuition_fees_room_and_board_in_state":"3783","tuition_fees_room_and_board_out_of_state":"14745","chrg_tuition_fees_not_avail":null,"hide":"0","pri":"10841"},{"year_pub":"2014","atp_code":"1893","asc_code":"1893281900","orgid":"1214","unitid":"222062","sector":"4","org_name":"Walters State Community College","state":"TN","tuition_fees_projected":"N","room_only":null,"room_and_board":null,"tuition_and_fees_in_state":"3990","tuition_and_fees_out_of_state":"15606","tuition_fees_room_and_board_in_state":"3990","tuition_fees_room_and_board_out_of_state":"15606","chrg_tuition_fees_not_avail":"N","hide":"0","pri":"7681"},{"year_pub":"2015","atp_code":"1893","asc_code":"1893281900","orgid":"1214","unitid":"222062","sector":"4","org_name":"Walters State Community College","state":"TN","tuition_fees_projected":"N","room_only":null,"room_and_board":null,"tuition_and_fees_in_state":"4116","tuition_and_fees_out_of_state":"16086","tuition_fees_room_and_board_in_state":"4116","tuition_fees_room_and_board_out_of_state":"16086","chrg_tuition_fees_not_avail":"N","hide":"0","pri":"3233"},{"year_pub":"2016","atp_code":"1893","asc_code":"1893281900","orgid":"1214","unitid":"222062","sector":"4","org_name":"Walters State Community College","state":"TN","tuition_fees_projected":"N","room_only":null,"room_and_board":null,"tuition_and_fees_in_state":"4218","tuition_and_fees_out_of_state":"16464","tuition_fees_room_and_board_in_state":"4218","tuition_fees_room_and_board_out_of_state":"16464","chrg_tuition_fees_not_avail":"N","hide":"0","pri":"61615"},{"year_pub":"2017","atp_code":"1893","asc_code":"1893281900","orgid":"1214","unitid":"222062","sector":"4","org_name":"Walters State Community College","state":"TN","tuition_fees_projected":"N","room_only":null,"room_and_board":null,"tuition_and_fees_in_state":"4320","tuition_and_fees_out_of_state":"16896","tuition_fees_room_and_board_in_state":"4320","tuition_fees_room_and_board_out_of_state":"16896","chrg_tuition_fees_not_avail":"N","hide":"0","pri":"62800"},{"year_pub":"2018","atp_code":"1893","asc_code":"1893281900","orgid":"1214","unitid":"222062","sector":"4","org_name":"Walters State Community College","state":"TN","tuition_fees_projected":"N","room_only":null,"room_and_board":null,"tuition_and_fees_in_state":"4428","tuition_and_fees_out_of_state":"13194","tuition_fees_room_and_board_in_state":"4428","tuition_fees_room_and_board_out_of_state":"13194","chrg_tuition_fees_not_avail":"N","hide":"0","pri":"66117"}]